mu_pipelines_driver/__init__.py
mu_pipelines_driver/__main__.py
mu_pipelines_driver/job_driver.py
mu_pipelines_driver/run_config.py
mu_pipelines_driver/ioc/destination_module_mapping.py
mu_pipelines_driver/ioc/execute_module_mapping.py
mu_pipelines_driver/ioc/import_function.py
mu_pipelines_driver/ioc/import_mapped_class.py
mu_pipelines_driver/ioc/ioc_container.py
mu_pipelines_driver/ioc/update_context.py
mu_pipelines_driver-0.5.0.dist-info/entry_points.txt
mu_pipelines_driver-0.5.0.dist-info/licenses/LICENSE
mu_pipelines_driver-0.5.0.dist-info/WHEEL
mu_pipelines_driver-0.5.0.dist-info/METADATA
mu_pipelines_driver-0.5.0.dist-info/RECORD
