Metadata-Version: 2.4
Name: mu_pipelines_driver
Version: 0.5.0
Summary: mu_pipelines_driver
Keywords: data movement,spark,etl
Author-email: MosaicSoft <mupipelines@gmail.com>
Requires-Python: >=3.11
Classifier: Programming Language :: Python :: 3
License-File: LICENSE
Requires-Dist: mu-pipelines-configuration-provider >=0.1.0
Requires-Dist: mu-pipelines-interfaces >=0.1.4
Requires-Dist: mu-pipelines-execute-spark ; extra == "spark"
Requires-Dist: mu-pipelines-destination-spark ; extra == "spark"
Project-URL: documentation, https://mosaicsoft-data.github.io/mu-pipelines-doc/
Provides-Extra: spark
